iostat_context/__init__.py
iostat_context-0.1.3.dist-info/LICENSE
iostat_context-0.1.3.dist-info/WHEEL
iostat_context-0.1.3.dist-info/METADATA
iostat_context-0.1.3.dist-info/RECORD
