Metadata-Version: 2.1
Name: iostat-context
Version: 0.1.3
Summary: A context manager for iostat.
License: GPL-3.0-or-later
Author: Gregory C. Oakes
Author-email: gregoryoakes@fastmail.com
Requires-Python: >=2.7, !=3.0.*, !=3.1.*, !=3.2.*, !=3.3.*, !=3.4.*, !=3.5.*
Classifier: License :: OSI Approved :: GNU General Public License v3 or later (GPLv3+)
Classifier: Programming Language :: Python :: 2
Classifier: Programming Language :: Python :: 2.7
Classifier: Programming Language :: Python :: 3
Classifier: Programming Language :: Python :: 3.6
Classifier: Programming Language :: Python :: 3.7
Classifier: Programming Language :: Python :: 3.8
Requires-Dist: backports.shutil_which (>=3.5.2,<4.0.0); python_version >= "2.7" and python_version < "3.0"
Requires-Dist: serde (>=0.8.0,<0.9.0)
